README.md
setup.py
MakeTreeDir/__init__.py
MakeTreeDir/makedir.py
MakeTreeDir.egg-info/PKG-INFO
MakeTreeDir.egg-info/SOURCES.txt
MakeTreeDir.egg-info/dependency_links.txt
MakeTreeDir.egg-info/not-zip-safe
MakeTreeDir.egg-info/top_level.txt