Metadata-Version: 2.1
Name: MakeTreeDir
Version: 0.1.4
Summary: OS wrapper python package which checks if a given folder tree path exists and creates them.
Home-page: https://github.com/Sreekiranar/MakeTreeDir.git
Author-email: sreekiranar@gmail.com
License: MIT
Platform: UNKNOWN
